Metadata-Version: 1.0
Name: useinf
Version: 1.0
Summary: Helper on USE IT in Russia
Home-page: UNKNOWN
Author: UNKNOWN
Author-email: andrewia2002@yandex.ru
License: UNKNOWN
Platform: UNKNOWN
